HandlerAPI/HandlerAPI.py
HandlerAPI/__init__.py
HandlerAPI-0.4.5.dist-info/LICENSE
HandlerAPI-0.4.5.dist-info/METADATA
HandlerAPI-0.4.5.dist-info/WHEEL
HandlerAPI-0.4.5.dist-info/top_level.txt
HandlerAPI-0.4.5.dist-info/RECORD
